README.md
setup.cfg
setup.py
gepace/__init__.py
gepace/pace.py
gepace/simulator.py
gepace.egg-info/PKG-INFO
gepace.egg-info/SOURCES.txt
gepace.egg-info/dependency_links.txt
gepace.egg-info/entry_points.txt
gepace.egg-info/requires.txt
gepace.egg-info/top_level.txt
gepace/tango/__init__.py
gepace/tango/server/__init__.py
gepace/tango/server/pace.py