Metadata-Version: 2.1
Name: gepace
Version: 1.1.2
Summary: GE Pace library
Home-page: https://github.com/tiagocoutinho/gepace
Author: Tiago Coutinho
Author-email: tcoutinho@cells.es
License: LGPLv3
Keywords: GE,pace,pace 5000,pace 6000,library,tango,simulator
Platform: UNKNOWN
Classifier: Development Status :: 2 - Pre-Alpha
Classifier: Intended Audience :: Developers
Classifier: Natural Language :: English
Classifier: Programming Language :: Python :: 3
Classifier: Programming Language :: Python :: 3.5
Classifier: Programming Language :: Python :: 3.6
Classifier: Programming Language :: Python :: 3.7
Classifier: Programming Language :: Python :: 3.8
Requires-Python: >=3.5
Provides-Extra: tango
Provides-Extra: simulator
